{
  "站街主属性": "7242",
  "装备主属性百分比(%)": "0",
  "天赋来源主属性百分比(%)": "0",
  "幻想主属性百分比(%)": "15",
  "其他主属性百分比(%)": "0",
  "转化系数": "0.6",
  "武器固定攻击力": "307",
  "模组固定攻击力": "60",
  "其他固定攻击力": "0",
  "装备攻击力百分比(%)": "6",
  "天赋攻击力百分比(%)": "0",
  "其他攻击力百分比(%)": "0",
  "精炼攻击力": "912",
  "本元素攻击力": "40",
  "全元素攻击力": "264",
  "本元素攻击力百分比(%)": "0",
  "全元素攻击力百分比(%)": "0",
  "暴击固定值": "40260",
  "急速固定值": "399",
  "幸运固定值": "56639",
  "精通固定值": "2256",
  "全能固定值": "5380",
  "一般增伤(%)": "0",
  "本元素增伤(%)": "19.7",
  "全元素增伤(%)": "0.72",
  "敌人物理防御": "9935",
  "敌人法术防御": "2018",
  "防御系数常数": "23205",
  "爆伤(%)": "75",
  "百分比穿防(%)": "0",
  "固定穿防": "0"
}